README.md
setup.py
lib/jumpserver_sync/__init__.py
lib/jumpserver_sync/application.py
lib/jumpserver_sync/assets.py
lib/jumpserver_sync/utils.py
lib/jumpserver_sync/workflow.py
lib/jumpserver_sync/jumpserver/__init__.py
lib/jumpserver_sync/jumpserver/clients.py
lib/jumpserver_sync/providers/__init__.py
lib/jumpserver_sync/providers/aws.py
lib/jumpserver_sync/providers/base.py
lib/jumpserver_sync2.egg-info/PKG-INFO
lib/jumpserver_sync2.egg-info/SOURCES.txt
lib/jumpserver_sync2.egg-info/dependency_links.txt
lib/jumpserver_sync2.egg-info/entry_points.txt
lib/jumpserver_sync2.egg-info/not-zip-safe
lib/jumpserver_sync2.egg-info/requires.txt
lib/jumpserver_sync2.egg-info/top_level.txt