Metadata-Version: 2.1
Name: jumpserver-sync2
Version: 0.2.2
Summary: Tools to sync large amount of instance into Jumpserver.
Home-page: UNKNOWN
Author: comver
Author-email: comver@qq.com
License: MIT
Keywords: jumpserver,python,cloud,aws
Platform: UNKNOWN
Classifier: Operating System :: OS Independent
Classifier: License :: OSI Approved :: MIT License
Classifier: Programming Language :: Python :: 3.5
Classifier: Programming Language :: Python :: 3.6
Classifier: Programming Language :: Python :: 3.7
Requires-Python: >=3.5
